serializers/__init__.py
serializers/serialization.py
serializers/serializer.py
serializers/parsers/__init__.py
serializers/parsers/json_parser.py
serializers/parsers/parser_factory_method.py
serializers/parsers/pickle_parser.py
serializers/parsers/toml_parser.py
serializers/parsers/yaml_parser.py
mpserializer-1.0.2.dist-info/METADATA
mpserializer-1.0.2.dist-info/WHEEL
mpserializer-1.0.2.dist-info/top_level.txt
mpserializer-1.0.2.dist-info/RECORD
